{
  "common": {
    "parent": {
      "popup": {
        "main": [
          {
            "id": "add",
            "type": "item",
            "title": "$Add",
            "command": "addNodeByContext",
            "popupid": "channels",
            "children": [
              { "id": "node", "title": "$NewChannel" },
              { "id": "folder", "title": "$NewFolder" }
            ]
          },
          { "id": "3", "type": "divider" },
          { "id": "4", "type": "item", "title": "$Copy", "command": "copy" },
          { "id": "5", "type": "item", "title": "$Paste", "command": "paste", "check": "disablePaste" },
          { "id": "6", "type": "divider" },
          {
            "id": "7",
            "type": "item",
            "title": "Клонировать",
            "command": "dialog",
            "param": {
              "variant": "form",
              "style":{"height":210, "width":450},
              "title": "Клонировать",

              "meta": {
                "grid": [{ "id": "p1", "xs": 12, "class": "main" }],
                "spacing": 8,
                "p1": [{ "prop": "unitId", "title": "UnitId", "type": "input" }]
              },
              "data": {
                "p1": { "unitId": "" }
              }
            }
          },
          {
            "id": "8",
            "type": "item",
            "title": "Привязать к устройству",
            "command": "dialog",
            "param": { "variant": "tree", "title": "Выберите устройство", "id": "devicesx", "action": "grouplink" }
          },
          { "id": "10", "type": "divider" },
          { "id": "11", "type": "item", "title": "$Delete", "command": "delete" },
          { "id": "12", "type": "divider" },
          { "id": "13", "type": "remote", "title": "$PluginCommand", "popupid": "plugincommand" }
        ]
      },
      "defaultComponent": "channelfolder"
    },
    "child": {
      "popup": {
        "main": [
          {
            "id": "add",
            "type": "item",
            "title": "$Add",
            "command": "addNodeByContext",
            "popupid": "channels",
            "children": [
              { "id": "node", "title": "$NewChannel" },
              { "id": "folder", "title": "$NewFolder" }
            ]
          },
          { "id": "3", "type": "divider" },
          { "id": "4", "type": "item", "title": "$Copy", "command": "copy" },
          { "id": "5", "type": "item", "title": "$Paste", "command": "paste", "check": "disablePaste" },
          { "id": "6", "type": "divider" },
          { "id": "7", "type": "item", "title": "$Delete", "command": "delete" },
          { "id": "8", "type": "divider" },
          { "id": "9", "type": "remote", "title": "$PluginCommand", "popupid": "plugincommand" }
        ]
      },
      "defaultComponent": "channelview"
    }
  }
}
